{
	"gui_light": "front",
	"credit": "Made with Blockbench",
	"textures": {
		"0": "spellbladenext:item/pillar_of_the_monkey_king",
		"particle": "spellbladenext:item/pillar_of_the_monkey_king"
	},
	"elements": [
		{
			"name": "PILLAR_0",
			"from": [0, 0, 12.66667],
			"to": [3.33333, 0.66667, 16],
			"faces": {
				"north": {"uv": [12.66667, 2.66667, 16, 3.33333], "texture": "#0"},
				"east": {"uv": [12.66667, 0, 13.33333, 3.33333], "rotation": 270, "texture": "#0"},
				"south": {"uv": [12.66667, 0, 16, 0.66667], "rotation": 180, "texture": "#0"},
				"west": {"uv": [15.33333, 0, 16, 3.33333], "rotation": 90, "texture": "#0"},
				"up": {"uv": [12.66667, 0, 16, 3.33333], "rotation": 180, "texture": "#0"},
				"down": {"uv": [16, 0, 12.66667, 3.33333], "texture": "#0"}
			}
		},
		{
			"name": "PILLAR_1",
			"from": [3.33333, 0, 11.33333],
			"to": [4.66667, 0.66667, 14],
			"faces": {
				"north": {"uv": [11.33333, 4, 12.66667, 4.66667], "texture": "#0"},
				"east": {"uv": [11.33333, 2, 12, 4.66667], "rotation": 270, "texture": "#0"},
				"south": {"uv": [11.33333, 2, 12.66667, 2.66667], "rotation": 180, "texture": "#0"},
				"west": {"uv": [12, 2, 12.66667, 4.66667], "rotation": 90, "texture": "#0"},
				"up": {"uv": [11.33333, 2, 12.66667, 4.66667], "rotation": 180, "texture": "#0"},
				"down": {"uv": [12.66667, 2, 11.33333, 4.66667], "texture": "#0"}
			}
		},
		{
			"name": "PILLAR_2",
			"from": [2, 0, 11.33333],
			"to": [3.33333, 0.66667, 12.66667],
			"faces": {
				"north": {"uv": [12.66667, 4, 14, 4.66667], "texture": "#0"},
				"east": {"uv": [12.66667, 3.33333, 13.33333, 4.66667], "rotation": 270, "texture": "#0"},
				"south": {"uv": [12.66667, 3.33333, 14, 4], "rotation": 180, "texture": "#0"},
				"west": {"uv": [13.33333, 3.33333, 14, 4.66667], "rotation": 90, "texture": "#0"},
				"up": {"uv": [12.66667, 3.33333, 14, 4.66667], "rotation": 180, "texture": "#0"},
				"down": {"uv": [14, 3.33333, 12.66667, 4.66667], "texture": "#0"}
			}
		},
		{
			"name": "PILLAR_3",
			"from": [4.66667, 0, 10],
			"to": [5.33333, 0.66667, 12],
			"faces": {
				"north": {"uv": [10.66667, 5.33333, 11.33333, 6], "texture": "#0"},
				"east": {"uv": [10.66667, 4, 11.33333, 6], "rotation": 270, "texture": "#0"},
				"south": {"uv": [10.66667, 4, 11.33333, 4.66667], "rotation": 180, "texture": "#0"},
				"west": {"uv": [10.66667, 4, 11.33333, 6], "rotation": 90, "texture": "#0"},
				"up": {"uv": [10.66667, 4, 11.33333, 6], "rotation": 180, "texture": "#0"},
				"down": {"uv": [11.33333, 4, 10.66667, 6], "texture": "#0"}
			}
		},
		{
			"name": "PILLAR_4",
			"from": [5.33333, 0, 9.33333],
			"to": [6, 0.66667, 11.33333],
			"faces": {
				"north": {"uv": [10, 6, 10.66667, 6.66667], "texture": "#0"},
				"east": {"uv": [10, 4.66667, 10.66667, 6.66667], "rotation": 270, "texture": "#0"},
				"south": {"uv": [10, 4.66667, 10.66667, 5.33333], "rotation": 180, "texture": "#0"},
				"west": {"uv": [10, 4.66667, 10.66667, 6.66667], "rotation": 90, "texture": "#0"},
				"up": {"uv": [10, 4.66667, 10.66667, 6.66667], "rotation": 180, "texture": "#0"},
				"down": {"uv": [10.66667, 4.66667, 10, 6.66667], "texture": "#0"}
			}
		},
		{
			"name": "PILLAR_5",
			"from": [4, 0, 10.66667],
			"to": [4.66667, 0.66667, 11.33333],
			"faces": {
				"north": {"uv": [11.33333, 4.66667, 12, 5.33333], "texture": "#0"},
				"east": {"uv": [11.33333, 4.66667, 12, 5.33333], "rotation": 270, "texture": "#0"},
				"south": {"uv": [11.33333, 4.66667, 12, 5.33333], "rotation": 180, "texture": "#0"},
				"west": {"uv": [11.33333, 4.66667, 12, 5.33333], "rotation": 90, "texture": "#0"},
				"up": {"uv": [11.33333, 4.66667, 12, 5.33333], "rotation": 180, "texture": "#0"},
				"down": {"uv": [12, 4.66667, 11.33333, 5.33333], "texture": "#0"}
			}
		},
		{
			"name": "PILLAR_6",
			"from": [6, 0, 8.66667],
			"to": [6.66667, 0.66667, 10.66667],
			"faces": {
				"north": {"uv": [9.33333, 6.66667, 10, 7.33333], "texture": "#0"},
				"east": {"uv": [9.33333, 5.33333, 10, 7.33333], "rotation": 270, "texture": "#0"},
				"south": {"uv": [9.33333, 5.33333, 10, 6], "rotation": 180, "texture": "#0"},
				"west": {"uv": [9.33333, 5.33333, 10, 7.33333], "rotation": 90, "texture": "#0"},
				"up": {"uv": [9.33333, 5.33333, 10, 7.33333], "rotation": 180, "texture": "#0"},
				"down": {"uv": [10, 5.33333, 9.33333, 7.33333], "texture": "#0"}
			}
		},
		{
			"name": "PILLAR_7",
			"from": [6.66667, 0, 8],
			"to": [7.33333, 0.66667, 10],
			"faces": {
				"north": {"uv": [8.66667, 7.33333, 9.33333, 8], "texture": "#0"},
				"east": {"uv": [8.66667, 6, 9.33333, 8], "rotation": 270, "texture": "#0"},
				"south": {"uv": [8.66667, 6, 9.33333, 6.66667], "rotation": 180, "texture": "#0"},
				"west": {"uv": [8.66667, 6, 9.33333, 8], "rotation": 90, "texture": "#0"},
				"up": {"uv": [8.66667, 6, 9.33333, 8], "rotation": 180, "texture": "#0"},
				"down": {"uv": [9.33333, 6, 8.66667, 8], "texture": "#0"}
			}
		},
		{
			"name": "PILLAR_8",
			"from": [7.33333, 0, 7.33333],
			"to": [8, 0.66667, 9.33333],
			"faces": {
				"north": {"uv": [8, 8, 8.66667, 8.66667], "texture": "#0"},
				"east": {"uv": [8, 6.66667, 8.66667, 8.66667], "rotation": 270, "texture": "#0"},
				"south": {"uv": [8, 6.66667, 8.66667, 7.33333], "rotation": 180, "texture": "#0"},
				"west": {"uv": [8, 6.66667, 8.66667, 8.66667], "rotation": 90, "texture": "#0"},
				"up": {"uv": [8, 6.66667, 8.66667, 8.66667], "rotation": 180, "texture": "#0"},
				"down": {"uv": [8.66667, 6.66667, 8, 8.66667], "texture": "#0"}
			}
		},
		{
			"name": "PILLAR_9",
			"from": [8, 0, 6.66667],
			"to": [8.66667, 0.66667, 8.66667],
			"faces": {
				"north": {"uv": [7.33333, 8.66667, 8, 9.33333], "texture": "#0"},
				"east": {"uv": [7.33333, 7.33333, 8, 9.33333], "rotation": 270, "texture": "#0"},
				"south": {"uv": [7.33333, 7.33333, 8, 8], "rotation": 180, "texture": "#0"},
				"west": {"uv": [7.33333, 7.33333, 8, 9.33333], "rotation": 90, "texture": "#0"},
				"up": {"uv": [7.33333, 7.33333, 8, 9.33333], "rotation": 180, "texture": "#0"},
				"down": {"uv": [8, 7.33333, 7.33333, 9.33333], "texture": "#0"}
			}
		},
		{
			"name": "PILLAR_10",
			"from": [8.66667, 0, 6],
			"to": [9.33333, 0.66667, 8],
			"faces": {
				"north": {"uv": [6.66667, 9.33333, 7.33333, 10], "texture": "#0"},
				"east": {"uv": [6.66667, 8, 7.33333, 10], "rotation": 270, "texture": "#0"},
				"south": {"uv": [6.66667, 8, 7.33333, 8.66667], "rotation": 180, "texture": "#0"},
				"west": {"uv": [6.66667, 8, 7.33333, 10], "rotation": 90, "texture": "#0"},
				"up": {"uv": [6.66667, 8, 7.33333, 10], "rotation": 180, "texture": "#0"},
				"down": {"uv": [7.33333, 8, 6.66667, 10], "texture": "#0"}
			}
		},
		{
			"name": "PILLAR_11",
			"from": [9.33333, 0, 5.33333],
			"to": [10, 0.66667, 7.33333],
			"faces": {
				"north": {"uv": [6, 10, 6.66667, 10.66667], "texture": "#0"},
				"east": {"uv": [6, 8.66667, 6.66667, 10.66667], "rotation": 270, "texture": "#0"},
				"south": {"uv": [6, 8.66667, 6.66667, 9.33333], "rotation": 180, "texture": "#0"},
				"west": {"uv": [6, 8.66667, 6.66667, 10.66667], "rotation": 90, "texture": "#0"},
				"up": {"uv": [6, 8.66667, 6.66667, 10.66667], "rotation": 180, "texture": "#0"},
				"down": {"uv": [6.66667, 8.66667, 6, 10.66667], "texture": "#0"}
			}
		},
		{
			"name": "PILLAR_12",
			"from": [10, 0, 4.66667],
			"to": [10.66667, 0.66667, 6.66667],
			"faces": {
				"north": {"uv": [5.33333, 10.66667, 6, 11.33333], "texture": "#0"},
				"east": {"uv": [5.33333, 9.33333, 6, 11.33333], "rotation": 270, "texture": "#0"},
				"south": {"uv": [5.33333, 9.33333, 6, 10], "rotation": 180, "texture": "#0"},
				"west": {"uv": [5.33333, 9.33333, 6, 11.33333], "rotation": 90, "texture": "#0"},
				"up": {"uv": [5.33333, 9.33333, 6, 11.33333], "rotation": 180, "texture": "#0"},
				"down": {"uv": [6, 9.33333, 5.33333, 11.33333], "texture": "#0"}
			}
		},
		{
			"name": "PILLAR_13",
			"from": [10.66667, 0, 4],
			"to": [11.33333, 0.66667, 6],
			"faces": {
				"north": {"uv": [4.66667, 11.33333, 5.33333, 12], "texture": "#0"},
				"east": {"uv": [4.66667, 10, 5.33333, 12], "rotation": 270, "texture": "#0"},
				"south": {"uv": [4.66667, 10, 5.33333, 10.66667], "rotation": 180, "texture": "#0"},
				"west": {"uv": [4.66667, 10, 5.33333, 12], "rotation": 90, "texture": "#0"},
				"up": {"uv": [4.66667, 10, 5.33333, 12], "rotation": 180, "texture": "#0"},
				"down": {"uv": [5.33333, 10, 4.66667, 12], "texture": "#0"}
			}
		},
		{
			"name": "PILLAR_14",
			"from": [11.33333, 0, 2],
			"to": [12, 0.66667, 5.33333],
			"faces": {
				"north": {"uv": [4, 13.33333, 4.66667, 14], "texture": "#0"},
				"east": {"uv": [4, 10.66667, 4.66667, 14], "rotation": 270, "texture": "#0"},
				"south": {"uv": [4, 10.66667, 4.66667, 11.33333], "rotation": 180, "texture": "#0"},
				"west": {"uv": [4, 10.66667, 4.66667, 14], "rotation": 90, "texture": "#0"},
				"up": {"uv": [4, 10.66667, 4.66667, 14], "rotation": 180, "texture": "#0"},
				"down": {"uv": [4.66667, 10.66667, 4, 14], "texture": "#0"}
			}
		},
		{
			"name": "PILLAR_15",
			"from": [12, 0, 2],
			"to": [14, 0.66667, 4.66667],
			"faces": {
				"north": {"uv": [2, 13.33333, 4, 14], "texture": "#0"},
				"east": {"uv": [2, 11.33333, 2.66667, 14], "rotation": 270, "texture": "#0"},
				"south": {"uv": [2, 11.33333, 4, 12], "rotation": 180, "texture": "#0"},
				"west": {"uv": [3.33333, 11.33333, 4, 14], "rotation": 90, "texture": "#0"},
				"up": {"uv": [2, 11.33333, 4, 14], "rotation": 180, "texture": "#0"},
				"down": {"uv": [4, 11.33333, 2, 14], "texture": "#0"}
			}
		},
		{
			"name": "PILLAR_16",
			"from": [14, 0, 0],
			"to": [16, 0.66667, 3.33333],
			"faces": {
				"north": {"uv": [0, 15.33333, 2, 16], "texture": "#0"},
				"east": {"uv": [0, 12.66667, 0.66667, 16], "rotation": 270, "texture": "#0"},
				"south": {"uv": [0, 12.66667, 2, 13.33333], "rotation": 180, "texture": "#0"},
				"west": {"uv": [1.33333, 12.66667, 2, 16], "rotation": 90, "texture": "#0"},
				"up": {"uv": [0, 12.66667, 2, 16], "rotation": 180, "texture": "#0"},
				"down": {"uv": [2, 12.66667, 0, 16], "texture": "#0"}
			}
		},
		{
			"name": "PILLAR_17",
			"from": [12.66667, 0, 0],
			"to": [14, 0.66667, 2],
			"faces": {
				"north": {"uv": [2, 15.33333, 3.33333, 16], "texture": "#0"},
				"east": {"uv": [2, 14, 2.66667, 16], "rotation": 270, "texture": "#0"},
				"south": {"uv": [2, 14, 3.33333, 14.66667], "rotation": 180, "texture": "#0"},
				"west": {"uv": [2.66667, 14, 3.33333, 16], "rotation": 90, "texture": "#0"},
				"up": {"uv": [2, 14, 3.33333, 16], "rotation": 180, "texture": "#0"},
				"down": {"uv": [3.33333, 14, 2, 16], "texture": "#0"}
			}
		}
	],
	"display": {
		"thirdperson_righthand": {
			"rotation": [-45, 0, -90],
			"translation": [7.5, 0.75, 2.25],
			"scale": [1.65, 1, 1.65]
		},
		"thirdperson_lefthand": {
			"rotation": [-45, -180, -90],
			"translation": [-7.5, 0.75, 2.25],
			"scale": [1.65, 1, 1.65]
		},
		"firstperson_righthand": {
			"rotation": [-45, 0, -90],
			"translation": [8, 0.75, 3.5],
			"scale": [1.65, 1, 1.65]
		},
		"firstperson_lefthand": {
			"rotation": [-130, 0, -90],
			"translation": [8, 0.75, 3.5],
			"scale": [1.65, 1, 1.65]
		},
		"ground": {
			"rotation": [-45, 0, -90],
			"translation": [8, 0.75, 3.5],
			"scale": [1.65, 1, 1.65]
		},
		"gui": {
			"rotation": [-90, -90, 0],
			"translation": [0.25, 0, -8]
		},
		"head": {
			"rotation": [-45, 0, -90],
			"translation": [8, 0.75, 3.5],
			"scale": [1.65, 1, 1.65]
		},
		"fixed": {
			"rotation": [-90, 0, 0],
			"translation": [-0.75, -0.75, -9.25]
		}
	},
	"groups": [
		{
			"name": "PILLAR",
			"origin": [8, 8, 8],
			"color": 0,
			"children": [0, 1, 2, 3, 4, 5, 6, 7, 8, 9, 10, 11, 12, 13, 14, 15, 16, 17]
		}
	]
}